foundation/__init__.py
foundation/core/__init__.py
foundation/core/optional/__init__.py
icloudpd_web/__init__.py
icloudpd_web/app.py
icloudpd_web/cli.py
icloudpd_web/dev.py
icloudpd_web/main.py
icloudpd_web/websockets.py
icloudpd_web/api/__init__.py
icloudpd_web/api/apprise_handler.py
icloudpd_web/api/authentication_local.py
icloudpd_web/api/aws_handler.py
icloudpd_web/api/client_handler.py
icloudpd_web/api/data_models.py
icloudpd_web/api/download_option_utils.py
icloudpd_web/api/error.py
icloudpd_web/api/icloud_utils.py
icloudpd_web/api/logger.py
icloudpd_web/api/policy_handler.py
icloudpd_web/webapp/404.html
icloudpd_web/webapp/index.html
icloudpd_web/webapp/index.txt
icloudpd_web/webapp/404/index.html
icloudpd_web/webapp/_next/static/EM5kYsHjJnuEPk60dkFYI/_buildManifest.js
icloudpd_web/webapp/_next/static/EM5kYsHjJnuEPk60dkFYI/_ssgManifest.js
icloudpd_web/webapp/_next/static/chunks/114.98fffe03960eebf5.js
icloudpd_web/webapp/_next/static/chunks/216-a0273a7f175960bf.js
icloudpd_web/webapp/_next/static/chunks/3d47b92a-fb3c74c927c50c8e.js
icloudpd_web/webapp/_next/static/chunks/4bd1b696-cf72ae8a39fa05aa.js
icloudpd_web/webapp/_next/static/chunks/558-bf591559cd85f952.js
icloudpd_web/webapp/_next/static/chunks/880-daf410979b3b5b50.js
icloudpd_web/webapp/_next/static/chunks/8e1d74a4-2f7a5e13a99d91ab.js
icloudpd_web/webapp/_next/static/chunks/964-9b249bc0ac5a9a8b.js
icloudpd_web/webapp/_next/static/chunks/9c4e2130-e3ad60263e2b4a5a.js
icloudpd_web/webapp/_next/static/chunks/f8025e75-6e5d38f5f511ecdd.js
icloudpd_web/webapp/_next/static/chunks/f97e080b-7366a2b9823cbd8f.js
icloudpd_web/webapp/_next/static/chunks/framework-f75312fc4004b783.js
icloudpd_web/webapp/_next/static/chunks/main-543a480f7b3f7c53.js
icloudpd_web/webapp/_next/static/chunks/main-app-af8be4957a7592a9.js
icloudpd_web/webapp/_next/static/chunks/polyfills-42372ed130431b0a.js
icloudpd_web/webapp/_next/static/chunks/webpack-452c9b2e4eaf47ac.js
icloudpd_web-2025.7.31.dist-info/METADATA
icloudpd_web-2025.7.31.dist-info/WHEEL
icloudpd_web-2025.7.31.dist-info/entry_points.txt
icloudpd_web-2025.7.31.dist-info/licenses/LICENSE
icloudpd_web-2025.7.31.dist-info/RECORD
