Metadata-Version: 2.4
Name: icloudpd-web
Version: 2025.7.31
Summary: Web application for iCloud Photos Downloader, based on icloudpd
Project-URL: Homepage, https://github.com/AirswitchAsa/icloudpd-web
Author-email: Qian Zhang <contact@qzsh.email>
License: Creative Commons Attribution-NonCommercial 4.0 International
License-File: LICENSE
Keywords: downloader,icloud,photos,webapp
Classifier: Development Status :: 4 - Beta
Classifier: License :: Other/Proprietary License
Classifier: Operating System :: OS Independent
Classifier: Programming Language :: Python :: 3
Classifier: Programming Language :: Python :: 3.12
Requires-Python: >=3.12
Requires-Dist: aiofiles>=24.1.0
Requires-Dist: apprise>=1.9.2
Requires-Dist: bcrypt>=4.0.0
Requires-Dist: boto3>=1.35.97
Requires-Dist: certifi==2024.12.14
Requires-Dist: click==8.1.8
Requires-Dist: click>=8.0.0
Requires-Dist: croniter>=6.0.0
Requires-Dist: fastapi>=0.109.0
Requires-Dist: flask==3.1.0
Requires-Dist: keyring==25.6.0
Requires-Dist: keyrings-alt==5.0.2
Requires-Dist: piexif==1.1.3
Requires-Dist: pillow>=11.1.0
Requires-Dist: python-dateutil==2.9.0.post0
Requires-Dist: python-socketio
Requires-Dist: pytz==2024.2
Requires-Dist: requests==2.32.3
Requires-Dist: schema==0.7.7
Requires-Dist: six==1.17.0
Requires-Dist: srp==1.0.22
Requires-Dist: stream-zip>=0.0.83
Requires-Dist: toml>=0.10.2
Requires-Dist: tqdm==4.67.1
Requires-Dist: typing-extensions==4.12.2
Requires-Dist: tzlocal==5.2
Requires-Dist: urllib3==1.26.20
Requires-Dist: uvicorn[standard]>=0.27.0
Requires-Dist: waitress==3.0.2
